app/__init__.py
app/__main__.py
app/modules/__init__.py
app/modules/common/__init__.py
app/modules/common/AD/__init__.py
app/modules/common/AD/F16_input/DH_technology_cost.xlsx
app/modules/common/AD/F16_input/__init__.py
app/modules/common/AD/F16_input/dat2xlsx.py
app/modules/common/AD/F16_input/load_name_map.dat
app/modules/common/AD/F16_input/load_profiles.dat
app/modules/common/AD/F16_input/main.py
app/modules/common/AD/F16_input/price_name_map.dat
app/modules/common/AD/F16_input/price_profiles.dat
app/modules/common/AD/F16_input/radiation_name_map.dat
app/modules/common/AD/F16_input/radiation_profiles.dat
app/modules/common/AD/F16_input/temperature_name_map.dat
app/modules/common/AD/F16_input/temperature_profiles.dat
app/modules/common/AD/F16_input/xlsx2dat.py
app/modules/common/AD/F16_input/static/__init__.py
app/modules/common/AD/F16_input/static/background.png
app/modules/common/CM/__init__.py
app/modules/common/CM/CM_TUWdispatch/__init__.py
app/modules/common/CM/CM_TUWdispatch/eng_format.py
app/modules/common/CM/CM_TUWdispatch/plot_bokeh.py
app/modules/common/CM/CM_TUWdispatch/preprocessing.py
app/modules/common/CM/CM_TUWdispatch/run_cm.py
app/modules/common/CM/CM_TUWdispatch/save_sol_to_json.py
app/modules/common/CM/CM_TUWdispatch/simpel_dispatch.py
app/modules/common/FEAT/__init__.py
app/modules/common/FEAT/F16/F_16.py
app/modules/common/FEAT/F16/F_16_server.py
app/modules/common/FEAT/F16/__init__.py
app/modules/common/FEAT/F16/download.js
app/modules/common/FEAT/F16/imageHTML.py
app/modules/common/FEAT/F16/input.xlsx
app/modules/common/FEAT/F16/snackbar.html
app/modules/common/FEAT/F16/spinner.html
app/modules/common/FEAT/F16/spinner2.html
app/modules/common/FEAT/F16/upload.js
hotmapsDispatch-0.0.1.dist-info/METADATA
hotmapsDispatch-0.0.1.dist-info/WHEEL
hotmapsDispatch-0.0.1.dist-info/entry_points.txt
hotmapsDispatch-0.0.1.dist-info/top_level.txt
hotmapsDispatch-0.0.1.dist-info/RECORD
