Metadata-Version: 2.1
Name: hotmapsDispatch
Version: 0.0.1
Summary: A web user interface for energy system modelling
Home-page: https://github.com/tuw-eeg/hotmapsDispatch/tree/dev
Author: Michal Hartner, Richard Büchele, David Schmidinger, Michael Gumhalter, Jeton Hasani
Author-email: hasani@eeg.tuwien.ac.at
License: Apache 2.0
Keywords: energy systems,optimisation,mathematical programming,web user innterfaace
Platform: UNKNOWN
Classifier: License :: OSI Approved :: Apache Software License
Classifier: Programming Language :: Python :: 3.6
Requires-Dist: bokeh (==0.12.10)
Requires-Dist: numpy
Requires-Dist: pandas
Requires-Dist: openpyxl
Requires-Dist: xlrd
Requires-Dist: matplotlib
Requires-Dist: pyomo
Requires-Dist: tornado (==4.5.3)
Requires-Dist: xlsxwriter
Requires-Dist: nodejs
